detect_exif.py
detect_exif-0.1.0.dist-info/licenses/LICENSE
detect_exif-0.1.0.dist-info/METADATA
detect_exif-0.1.0.dist-info/WHEEL
detect_exif-0.1.0.dist-info/entry_points.txt
detect_exif-0.1.0.dist-info/top_level.txt
detect_exif-0.1.0.dist-info/RECORD
