Metadata-Version: 2.4
Name: detect-exif
Version: 0.1.0
Summary: A simple commandline tool to remove the EXIF data from image files.
Author: Olaf Lipinski
License: MIT License
Project-URL: Homepage, https://github.com/olipinski/detect-exif
Project-URL: Bug Tracker, https://github.com/olipinski/detect-exif/issues
Classifier: Development Status :: 3 - Alpha
Classifier: Topic :: Software Development :: Libraries :: Python Modules
Classifier: Topic :: Utilities
Classifier: Topic :: Security
Classifier: License :: OSI Approved :: MIT License
Classifier: Operating System :: OS Independent
Classifier: Programming Language :: Python :: 3 :: Only
Classifier: Programming Language :: Python :: 3.9
Classifier: Programming Language :: Python :: 3.10
Classifier: Programming Language :: Python :: 3.11
Classifier: Programming Language :: Python :: 3.12
Classifier: Programming Language :: Python :: 3.13
Classifier: Natural Language :: English
Requires-Python: <3.14,>=3.9.0
License-File: LICENSE
Requires-Dist: pillow>=1.1.0
Requires-Dist: piexif
Dynamic: license-file
